<run><onStart></onStart><onLastGoalReached></onLastGoalReached><goal x="-73.56458675833333" y="45.49534341500000" type="gps" priority="100"></goal><goal x="-73.56463027666666" y="45.49535318833333" type="gps" priority="100"></goal><goal x="-73.56467791166666" y="45.49536072500000" type="gps" priority="100"></goal><goal x="-73.56471313166666" y="45.49532695000000" type="gps" priority="100"></goal><goal x="-73.56465910999999" y="45.49526727166667" type="gps" priority="100"></goal><goal x="-73.56451802666666" y="45.49529166000000" type="gps" priority="100"></goal></run>